{"version": 0.6, "generator": "Overpass API 0.7.62.11 87bfad18", "osm3s": {"timestamp_osm_base": "2026-05-18T14:54:02Z", "copyright": "The data included in this document is from www.openstreetmap.org. The data is made available under ODbL."}, "elements": [{"type": "node", "id": 30003404, "lat": 53.3903598, "lon": -2.8995075, "tags": {"amenity": "pub", "created_by": "JOSM", "name": "Halfway House"}}, {"type": "node", "id": 533860288, "lat": 53.390146, "lon": -2.8980928, "tags": {"bus": "yes", "highway": "bus_stop", "name": "WOOLTON ROAD/QUEENS DRIVE", "naptan:AtcoCode": "2800S43077A", "naptan:Bearing": "NW", "naptan:CommonName": "WOOLTON ROAD/QUEENS DRIVE", "naptan:Indicator": "WOOLTON ROAD/QUEENS DRIVE", "naptan:Landmark": "OPP TOWERS ROAD NR CORNER GREEN LANE", "naptan:NaptanCode": "merdjtjp", "naptan:Notes": "No Notes", "naptan:PlusbusZoneRef": "LVRPLCH", "naptan:ShortCommonName": "Queens Dr", "naptan:Street": "WOOLTON ROAD", "naptan:verified": "no", "public_transport": "platform", "source": "naptan_import"}}, {"type": "node", "id": 533860290, "lat": 53.3904536, "lon": -2.8990315, "tags": {"bus": "yes", "highway": "bus_stop", "name": "WOOLTON ROAD/QUEENS DRIVE", "naptan:AtcoCode": "2800S43077B", "naptan:Bearing": "E", "naptan:CommonName": "WOOLTON ROAD/QUEENS DRIVE", "naptan:Indicator": "WOOLTON ROAD/QUEENS DRIVE", "naptan:Landmark": "NR CORNER ELDRED ROAD OPP SHOPS", "naptan:NaptanCode": "merdjtjt", "naptan:Notes": "No Notes", "naptan:PlusbusZoneRef": "LVRPLCH", "naptan:ShortCommonName": "Queens Dr", "naptan:Street": "WOOLTON ROAD", "naptan:verified": "no", "public_transport": "platform", "source": "naptan_import"}}, {"type": "node", "id": 533860291, "lat": 53.392235, "lon": -2.9047685, "tags": {"bus": "yes", "highway": "bus_stop", "name": "WOOLTON ROAD/HEATHFIELD ROAD", "naptan:AtcoCode": "2800S43078A", "naptan:Bearing": "NW", "naptan:CommonName": "WOOLTON ROAD/HEATHFIELD ROAD", "naptan:Indicator": "WOOLTON ROAD/HEATHFIELD ROAD", "naptan:Landmark": "CORNER MONTCLAIR DRIVE OPP 205", "naptan:NaptanCode": "merdjtjw", "naptan:Notes": "No Notes", "naptan:PlusbusZoneRef": "LVRPLCH", "naptan:ShortCommonName": "Heathfield Rd", "naptan:Street": "WOOLTON ROAD", "naptan:verified": "no", "public_transport": "platform", "source": "naptan_import"}}, {"type": "node", "id": 533860293, "lat": 53.3919196, "lon": -2.9036941, "tags": {"bus": "yes", "highway": "bus_stop", "name": "WOOLTON ROAD/DUNBABIN ROAD", "naptan:AtcoCode": "2800S43078B", "naptan:Bearing": "SE", "naptan:CommonName": "WOOLTON ROAD/DUNBABIN ROAD", "naptan:Indicator": "WOOLTON ROAD/DUNBABIN ROAD", "naptan:Landmark": "O/S 215 NR BEAUCLAIR DRIVE", "naptan:NaptanCode": "merdjtma", "naptan:Notes": "No Notes", "naptan:PlusbusZoneRef": "LVRPLCH", "naptan:ShortCommonName": "Woolton/Dunbabin Rd", "naptan:Street": "WOOLTON ROAD", "naptan:verified": "no", "public_transport": "platform", "source": "naptan_import"}}, {"type": "node", "id": 2804294136, "lat": 53.3902743, "lon": -2.898801, "tags": {"addr:housenumber": "258", "addr:street": "Woolton Road", "amenity": "restaurant", "name": "Eton Place", "website": "https://etonplace-restaurant.co.uk/"}}, {"type": "node", "id": 4761621692, "lat": 53.3902956, "lon": -2.8988993, "tags": {"addr:city": "Liverpool", "addr:housenumber": "256", "addr:postcode": "L16 8NE", "addr:street": "Woolton Road", "amenity": "restaurant", "capacity": "100", "cuisine": "italian", "delivery": "no", "name": "Cucina di Vincenzo's", "opening_hours": "12:00-10:00", "outdoor_seating": "yes", "smoking": "no", "takeaway": "no"}}]}