{"version": 0.6, "generator": "Overpass API 0.7.62.11 87bfad18", "osm3s": {"timestamp_osm_base": "2026-05-18T15:08:18Z", "copyright": "The data included in this document is from www.openstreetmap.org. The data is made available under ODbL."}, "elements": [{"type": "node", "id": 25448278, "lat": 53.408047, "lon": -2.977798, "tags": {"name": "Liverpool Lime Street", "public_transport": "stop_position", "railway": "stop", "ref": "1", "train": "yes"}}, {"type": "node", "id": 348176545, "lat": 53.4084255, "lon": -2.9786084, "tags": {"addr:city": "Liverpool", "addr:housenumber": "7", "addr:postcode": "L1 1RJ", "addr:street": "Lime Street", "amenity": "pub", "brand": "Wetherspoon", "brand:wikidata": "Q6109362", "brand:wikipedia": "en:Wetherspoons", "cask_marque": "yes", "check_date": "2025-03-04", "dog": "no", "fhrs:id": "779717", "food": "yes", "name": "The North Western", "opening_hours": "Mo-Sa 06:00-00:00; Su 08:00-00:00", "phone": "+44 1517 096825", "real_ale": "yes", "website": "https://www.jdwetherspoon.com/pubs/all-pubs/england/merseyside/the-north-western-liverpool", "website:menu": "https://order.jdwetherspoon.com/venue/jdw/6486/menus"}}, {"type": "node", "id": 533856617, "lat": 53.4102489, "lon": -2.9756035, "tags": {"bench": "yes", "bus": "yes", "highway": "bus_stop", "name": "NORTON STREET/COACH STATION", "naptan:AtcoCode": "2800S42014A", "naptan:Bearing": "NW", "naptan:CommonName": "NORTON STREET/COACH STATION", "naptan:Indicator": "NORTON STREET", "naptan:Landmark": "OPP MIDLAND BANK O/S COACH STATION", "naptan:NaptanCode": "merdgwaj", "naptan:Notes": "No Notes", "naptan:PlusbusZoneRef": "LVRPLCH", "naptan:ShortCommonName": "Norton St/Coach Stn", "naptan:Street": "NORTON STREET", "naptan:verified": "no", "public_transport": "platform", "shelter": "yes", "source": "naptan_import"}}, {"type": "node", "id": 533856619, "lat": 53.4102342, "lon": -2.975197, "tags": {"bench": "yes", "bin": "no", "bus": "yes", "highway": "bus_stop", "lit": "yes", "name": "NORTON STREET", "naptan:AtcoCode": "2800S42014B", "naptan:Bearing": "S", "naptan:CommonName": "NORTON STREET", "naptan:Indicator": "NORTON STEET", "naptan:Landmark": "NEXT TO MIDLAND BANK", "naptan:NaptanCode": "merdgwam", "naptan:Notes": "No Notes", "naptan:PlusbusZoneRef": "LVRPLCH", "naptan:ShortCommonName": "Norton St", "naptan:Street": "NORTON STEET", "naptan:verified": "no", "public_transport": "platform", "shelter": "yes", "source": "naptan_import"}}, {"type": "node", "id": 533856639, "lat": 53.4098527, "lon": -2.9785722, "tags": {"bench": "no", "bin": "no", "bus": "yes", "highway": "bus_stop", "lit": "yes", "name": "COMMUTATION ROW/WELLINGTONS COLUMN", "naptan:AtcoCode": "2800S42017A", "naptan:Bearing": "S", "naptan:CommonName": "COMMUTATION ROW/WELLINGTONS COLUMN", "naptan:Indicator": "COMMUTATION ROW", "naptan:Landmark": "NR WELLINGTON'S COLUMN AND LIVERPOOL MUSEUM", "naptan:NaptanCode": "merdgwgd", "naptan:Notes": "No Notes", "naptan:PlusbusZoneRef": "LVRPLCH", "naptan:ShortCommonName": "Wellingtons Column", "naptan:Street": "COMMUTATION ROW", "naptan:verified": "no", "public_transport": "platform", "shelter": "no", "source": "naptan_import"}}, {"type": "node", "id": 533856655, "lat": 53.4075076, "lon": -2.9826945}, {"type": "node", "id": 533856657, "lat": 53.4077673, "lon": -2.9817201}, {"type": "node", "id": 533856658, "lat": 53.4078613, "lon": -2.9814983}, {"type": "node", "id": 533856659, "lat": 53.4076769, "lon": -2.9819478}, {"type": "node", "id": 533856661, "lat": 53.407581, "lon": -2.9821659}, {"type": "node", "id": 533856662, "lat": 53.4075449, "lon": -2.9829585}, {"type": "node", "id": 533856663, "lat": 53.4075801, "lon": -2.9832214}, {"type": "node", "id": 533856664, "lat": 53.4075097, "lon": -2.9817274, "tags": {"bench": "no", "bin": "no", "bus": "yes", "highway": "bus_stop", "lit": "yes", "name": "Queen Square Bus Station (alighting Only)", "naptan:AtcoCode": "2800S42023J", "naptan:CommonName": "Queen Square Bus Station (alighting Only)", "naptan:Indicator": "Alighting", "naptan:Landmark": "Queen Sq Alight Only", "naptan:NaptanCode": "merdgwpj", "naptan:Notes": "No Notes", "naptan:PlusbusZoneRef": "LVRPLCH", "naptan:ShortCommonName": "Queen Square", "naptan:Street": "Queen Square Alighting Only", "naptan:verified": "no", "public_transport": "platform", "shelter": "no", "source": "naptan_import"}}, {"type": "node", "id": 533856670, "lat": 53.408397, "lon": -2.9789159, "tags": {"bus": "yes", "highway": "bus_stop", "name": "LIME ST RAIL STATION", "naptan:AtcoCode": "2800S42024A", "naptan:Bearing": "S", "naptan:CommonName": "Lord Nelson Street", "naptan:Indicator": "Adjacent", "naptan:Landmark": "NR EMPIRE THEATRE", "naptan:NaptanCode": "merdgwtd", "naptan:Notes": "No Notes", "naptan:PlusbusZoneRef": "LVRPLCH", "naptan:ShortCommonName": "Lime St Station", "naptan:Street": "Lime Street", "naptan:verified": "no", "public_transport": "platform", "source": "naptan_import", "wheelchair": "yes"}}, {"type": "node", "id": 533856747, "lat": 53.4083921, "lon": -2.9816989, "tags": {"bus": "yes", "highway": "bus_stop", "name": "St Johns Lane", "naptan:AtcoCode": "2800S42042A", "naptan:Bearing": "NW", "naptan:CommonName": "St Johns Lane", "naptan:Indicator": "St Johns Lane", "naptan:Landmark": "St Johns Garden", "naptan:NaptanCode": "mertwpdw", "naptan:ShortCommonName": "St Johns Lane", "naptan:Street": "St Johns Lane", "naptan:verified": "no", "note": "matchday 917 service", "public_transport": "platform", "source": "naptan_import"}}, {"type": "node", "id": 533856793, "lat": 53.4093685, "lon": -2.9766365, "tags": {"bench": "yes", "bin": "no", "bus": "yes", "highway": "bus_stop", "lit": "yes", "name": "London Rd/stop A", "naptan:AtcoCode": "2800S42057C", "naptan:Bearing": "E", "naptan:CommonName": "London Rd/stop A", "naptan:Indicator": "London Road/stop A", "naptan:Landmark": "Stop A Nearest Lime Street", "naptan:NaptanCode": "merdjdjd", "naptan:Notes": "No Notes", "naptan:PlusbusZoneRef": "LVRPLCH", "naptan:ShortCommonName": "London Rd A", "naptan:Street": "London Road", "naptan:verified": "no", "public_transport": "platform", "shelter": "yes", "source": "naptan_import"}}, {"type": "node", "id": 533856795, "lat": 53.4093482, "lon": -2.9758236, "tags": {"bench": "yes", "bin": "no", "bus": "yes", "highway": "bus_stop", "lit": "yes", "name": "London Rd/stop B", "naptan:AtcoCode": "2800S42057D", "naptan:Bearing": "E", "naptan:CommonName": "London Rd/stop B", "naptan:Indicator": "London Road/stop B", "naptan:Landmark": "Shelter Nearest Rton Street", "naptan:NaptanCode": "merdjdjg", "naptan:Notes": "No Notes", "naptan:PlusbusZoneRef": "LVRPLCH", "naptan:ShortCommonName": "London Rd B", "naptan:Street": "London Road", "naptan:verified": "no", "public_transport": "platform", "shelter": "yes", "source": "naptan_import"}}, {"type": "node", "id": 533857360, "lat": 53.4094519, "lon": -2.9807154, "tags": {"bench": "no", "bin": "no", "bus": "yes", "highway": "bus_stop", "lit": "yes", "name": "William Brown St", "naptan:AtcoCode": "2800S42063A", "naptan:Bearing": "E", "naptan:CommonName": "William Brown St", "naptan:Indicator": "William Brown St", "naptan:Landmark": "Museum Entrance", "naptan:NaptanCode": "mermamaj", "naptan:Notes": "No Notes", "naptan:PlusbusZoneRef": "LVRPLCH", "naptan:ShortCommonName": "William Brown St", "naptan:Street": "William Brown St", "naptan:verified": "no", "public_transport": "platform", "shelter": "no", "source": "naptan_import"}}, {"type": "node", "id": 533857377, "lat": 53.4102409, "lon": -2.9831557, "tags": {"bus": "yes", "highway": "bus_stop", "name": "BYROM ST/SMART ONLY", "naptan:AtcoCode": "2800S42085A", "naptan:Bearing": "NE", "naptan:CommonName": "BYROM ST/SMART ONLY", "naptan:Indicator": "FONTENOY STREET/BYROM STREET", "naptan:Landmark": "NR DALE STREET AND TUNNEL ENTRANCE", "naptan:NaptanCode": "merdjdpt", "naptan:Notes": "No Notes", "naptan:PlusbusZoneRef": "LVRPLCH", "naptan:ShortCommonName": "Byrom St/Smart Only", "naptan:Street": "FONTENOY STREET", "naptan:verified": "no", "public_transport": "platform", "source": "naptan_import"}}, {"type": "node", "id": 534436265, "lat": 53.4078394, "lon": -2.9780918}, {"type": "node", "id": 534436267, "lat": 53.4081782, "lon": -2.9779322}, {"type": "node", "id": 534436269, "lat": 53.4079469, "lon": -2.9765944}, {"type": "node", "id": 534436270, "lat": 53.4076468, "lon": -2.9753923}, {"type": "node", "id": 534436303, "lat": 53.4076378, "lon": -2.9759508}, {"type": "node", "id": 534436305, "lat": 53.408017, "lon": -2.9780126}, {"type": "node", "id": 534436324, "lat": 53.4075553, "lon": -2.9760167}, {"type": "node", "id": 534436326, "lat": 53.4076841, "lon": -2.9767921}, {"type": "node", "id": 534436368, "lat": 53.4073989, "lon": -2.9753599}, {"type": "node", "id": 534436369, "lat": 53.4075899, "lon": -2.9766472}, {"type": "node", "id": 534438316, "lat": 53.407177, "lon": -2.9768052}, {"type": "node", "id": 551872944, "lat": 53.4077845, "lon": -2.9785985}, {"type": "node", "id": 681266131, "lat": 53.4079291, "lon": -2.9782427}, {"type": "node", "id": 1021462427, "lat": 53.407641, "lon": -2.9783695}, {"type": "node", "id": 1021462448, "lat": 53.4074763, "lon": -2.9759955}, {"type": "node", "id": 1241183502, "lat": 53.4083829, "lon": -2.9822638, "tags": {"addr:city": "Liverpool", "addr:postcode": "L1 1HF", "addr:street": "St Johns Lane", "amenity": "pub", "fhrs:id": "1064298", "name": "Doctor Duncan's", "outdoor_seating": "yes", "real_ale": "yes (a few, lots of craft ales too)", "source": "Bing & Memory", "website": "https://www.doctorduncansliverpool.com/"}}, {"type": "node", "id": 1241183538, "lat": 53.4083205, "lon": -2.9821283, "tags": {"addr:city": "Liverpool", "addr:postcode": "L1 1HF", "addr:street": "St Johns Lane", "amenity": "restaurant", "cuisine": "chinese", "name": "Tso's Oriental Buffet"}}, {"type": "node", "id": 2092815578, "lat": 53.4101005, "lon": -2.9750194}, {"type": "node", "id": 2092815579, "lat": 53.4101997, "lon": -2.9746095}, {"type": "node", "id": 2092815588, "lat": 53.4103852, "lon": -2.9752133}, {"type": "node", "id": 2092815590, "lat": 53.4104844, "lon": -2.9748034}, {"type": "node", "id": 2229242045, "lat": 53.4086588, "lon": -2.9777725}, {"type": "node", "id": 2261421076, "lat": 53.4078757, "lon": -2.9829227}, {"type": "node", "id": 2261421091, "lat": 53.4077585, "lon": -2.9831041}, {"type": "node", "id": 2261421093, "lat": 53.407709, "lon": -2.9837427}, {"type": "node", "id": 2261421098, "lat": 53.4077716, "lon": -2.9830724}, {"type": "node", "id": 2261421099, "lat": 53.407797, "lon": -2.9830185}, {"type": "node", "id": 2261421104, "lat": 53.4077575, "lon": -2.9831702}, {"type": "node", "id": 2261421106, "lat": 53.4077545, "lon": -2.9831377}, {"type": "node", "id": 2261421117, "lat": 53.4078258, "lon": -2.9829756}, {"type": "node", "id": 2261421122, "lat": 53.407658, "lon": -2.9833729}, {"type": "node", "id": 2261421128, "lat": 53.4077678, "lon": -2.9831982}, {"type": "node", "id": 2462951415, "lat": 53.4075473, "lon": -2.9754295}, {"type": "node", "id": 2462951475, "lat": 53.4079054, "lon": -2.9780639}, {"type": "node", "id": 2462951516, "lat": 53.407428, "lon": -2.9767617}, {"type": "node", "id": 2462951520, "lat": 53.4074572, "lon": -2.9771056}, {"type": "node", "id": 2462951527, "lat": 53.4074173, "lon": -2.9764541}, {"type": "node", "id": 2462953568, "lat": 53.4071553, "lon": -2.9763953}, {"type": "node", "id": 2702384791, "lat": 53.4085582, "lon": -2.977826}, {"type": "node", "id": 2704294802, "lat": 53.4094068, "lon": -2.9739465, "tags": {"amenity": "atm", "brand": "Tesco Bank", "brand:wikidata": "Q487494", "name": "Tesco ATM", "operator": "Tesco"}}, {"type": "node", "id": 2767005075, "lat": 53.4095627, "lon": -2.9753281}, {"type": "node", "id": 2767005078, "lat": 53.409759, "lon": -2.9755876}, {"type": "node", "id": 2767005081, "lat": 53.4096193, "lon": -2.9755496}, {"type": "node", "id": 2767005085, "lat": 53.4093861, "lon": -2.9756104}, {"type": "node", "id": 2767005094, "lat": 53.4093819, "lon": -2.9762463}, {"type": "node", "id": 2767005100, "lat": 53.4094183, "lon": -2.9775041}, {"type": "node", "id": 2767005112, "lat": 53.4095324, "lon": -2.9756135}, {"type": "node", "id": 2767005113, "lat": 53.4097324, "lon": -2.9753772}, {"type": "node", "id": 2767005118, "lat": 53.4096318, "lon": -2.9754989}, {"type": "node", "id": 2767005122, "lat": 53.4095964, "lon": -2.9753515}, {"type": "node", "id": 2767005151, "lat": 53.4097993, "lon": -2.9754235}, {"type": "node", "id": 2767005153, "lat": 53.409595, "lon": -2.9751965}, {"type": "node", "id": 2767005158, "lat": 53.4096821, "lon": -2.975593}, {"type": "node", "id": 2767005166, "lat": 53.4095331, "lon": -2.9755256}, {"type": "node", "id": 2767005168, "lat": 53.409621, "lon": -2.9752145}, {"type": "node", "id": 2767005174, "lat": 53.409741, "lon": -2.9752095}, {"type": "node", "id": 2767005180, "lat": 53.4096395, "lon": -2.9751393}, {"type": "node", "id": 2767005188, "lat": 53.4095094, "lon": -2.9775229}, {"type": "node", "id": 2767005190, "lat": 53.4095406, "lon": -2.9762853}, {"type": "node", "id": 2767005201, "lat": 53.4095188, "lon": -2.9773859}, {"type": "node", "id": 2767005203, "lat": 53.4095382, "lon": -2.9751394}, {"type": "node", "id": 2767005209, "lat": 53.4096944, "lon": -2.9755429}, {"type": "node", "id": 2767005212, "lat": 53.4094123, "lon": -2.9773636}, {"type": "node", "id": 2767005246, "lat": 53.4093907, "lon": -2.9751328}, {"type": "node", "id": 2767005247, "lat": 53.4097179, "lon": -2.9753035}, {"type": "node", "id": 2767005257, "lat": 53.4095705, "lon": -2.9754565}, {"type": "node", "id": 2767005267, "lat": 53.4095511, "lon": -2.9761287}, {"type": "node", "id": 2767005270, "lat": 53.4095425, "lon": -2.9770993}, {"type": "node", "id": 2767006369, "lat": 53.4103033, "lon": -2.9781393}, {"type": "node", "id": 2767006370, "lat": 53.4105087, "lon": -2.9783357}, {"type": "node", "id": 2767006371, "lat": 53.4105392, "lon": -2.9780501}, {"type": "node", "id": 2767006372, "lat": 53.4106959, "lon": -2.978283}, {"type": "node", "id": 2767006373, "lat": 53.4103189, "lon": -2.978234}, {"type": "node", "id": 2767006374, "lat": 53.4104941, "lon": -2.9783799}, {"type": "node", "id": 2767006376, "lat": 53.4104114, "lon": -2.9778029}, {"type": "node", "id": 2767006377, "lat": 53.410572, "lon": -2.9779478}, {"type": "node", "id": 2767006378, "lat": 53.4106284, "lon": -2.9784856}, {"type": "node", "id": 2767006379, "lat": 53.4105676, "lon": -2.9781595}, {"type": "node", "id": 2767006381, "lat": 53.4105883, "lon": -2.9784486}, {"type": "node", "id": 2767006382, "lat": 53.4105963, "lon": -2.9784229}, {"type": "node", "id": 2767006383, "lat": 53.4105882, "lon": -2.9780943}, {"type": "node", "id": 4042536807, "lat": 53.4078498, "lon": -2.981353, "tags": {"bus": "yes", "name": "Liverpool Queen Square (Stand 8)", "public_transport": "stop_position"}}, {"type": "node", "id": 4261923762, "lat": 53.4075993, "lon": -2.9783843, "tags": {"name": "Liverpool Lime Street", "public_transport": "stop_position", "railway": "stop", "ref": "6", "train": "yes"}}, {"type": "node", "id": 4319286756, "lat": 53.4073517, "lon": -2.9784389, "tags": {"name": "Liverpool Lime Street", "public_transport": "stop_position", "railway": "stop", "ref": "10", "train": "yes"}}, {"type": "node", "id": 4319951101, "lat": 53.4086235, "lon": -2.9791887, "tags": {"name": "Liverpool Lime Street", "public_transport": "stop_position", "railway": "stop", "ref": "A", "train": "yes"}}, {"type": "node", "id": 4417907433, "lat": 53.4090352, "lon": -2.976544}, {"type": "node", "id": 4417907435, "lat": 53.4092257, "lon": -2.976533}, {"type": "node", "id": 4417907438, "lat": 53.4092262, "lon": -2.9763424}, {"type": "node", "id": 4417907450, "lat": 53.4090042, "lon": -2.975697}, {"type": "node", "id": 4417907453, "lat": 53.4091305, "lon": -2.9765368}, {"type": "node", "id": 4417907462, "lat": 53.4091449, "lon": -2.9762637}, {"type": "node", "id": 4417907466, "lat": 53.4090092, "lon": -2.97585}, {"type": "node", "id": 4417907480, "lat": 53.4090424, "lon": -2.9766884}, {"type": "node", "id": 4417907593, "lat": 53.4096046, "lon": -2.9738409}, {"type": "node", "id": 4417907599, "lat": 53.4092282, "lon": -2.9766847}, {"type": "node", "id": 4417907601, "lat": 53.4091463, "lon": -2.9763432}, {"type": "node", "id": 4417907610, "lat": 53.409229, "lon": -2.9768252}, {"type": "node", "id": 4417907622, "lat": 53.4092248, "lon": -2.9762613}, {"type": "node", "id": 4417907627, "lat": 53.4091935, "lon": -2.9755346}, {"type": "node", "id": 4417907637, "lat": 53.4086376, "lon": -2.9776544}, {"type": "node", "id": 4417907638, "lat": 53.4090013, "lon": -2.9755435}, {"type": "node", "id": 4417907639, "lat": 53.4092082, "lon": -2.9758383}, {"type": "node", "id": 4417907643, "lat": 53.4095832, "lon": -2.974121}, {"type": "node", "id": 4417907644, "lat": 53.4091989, "lon": -2.9756857}, {"type": "node", "id": 4417907649, "lat": 53.4092144, "lon": -2.9759706}, {"type": "node", "id": 4417907661, "lat": 53.4097119, "lon": -2.9738934}, {"type": "node", "id": 4417907675, "lat": 53.4096612, "lon": -2.9741621}, {"type": "node", "id": 4417914225, "lat": 53.4090481, "lon": -2.9768685}, {"type": "node", "id": 4501083370, "lat": 53.4076388, "lon": -2.9814175}, {"type": "node", "id": 4501084021, "lat": 53.4072822, "lon": -2.9826405}, {"type": "node", "id": 4501084039, "lat": 53.4077174, "lon": -2.9812725}, {"type": "node", "id": 4501084076, "lat": 53.4073721, "lon": -2.9820557}, {"type": "node", "id": 4501084082, "lat": 53.4073369, "lon": -2.9821844}, {"type": "node", "id": 4541108418, "lat": 53.4077838, "lon": -2.9787886, "tags": {"brand": "Merseyrail", "description": "Entrance to Lime Street (underground) station", "name": "Lime Street Low Level", "note": "leads to escalator and pedestrian subway (UK usage)", "railway": "subway_entrance", "wheelchair": "no"}}, {"type": "node", "id": 6003392253, "lat": 53.4071859, "lon": -2.9745372}, {"type": "node", "id": 6003392254, "lat": 53.4072042, "lon": -2.9745366}, {"type": "node", "id": 6003392255, "lat": 53.4072718, "lon": -2.9745102}, {"type": "node", "id": 6003392257, "lat": 53.4072861, "lon": -2.9746369}, {"type": "node", "id": 6003392258, "lat": 53.4073083, "lon": -2.9748254}, {"type": "node", "id": 6003392259, "lat": 53.4073187, "lon": -2.975078}, {"type": "node", "id": 6003392260, "lat": 53.4073366, "lon": -2.9753346}, {"type": "node", "id": 6003392262, "lat": 53.407336, "lon": -2.9759381}, {"type": "node", "id": 6003392263, "lat": 53.4073446, "lon": -2.97642}, {"type": "node", "id": 6003392264, "lat": 53.4073652, "lon": -2.976742}, {"type": "node", "id": 6003392265, "lat": 53.4074036, "lon": -2.9771604}, {"type": "node", "id": 6003392266, "lat": 53.4076079, "lon": -2.9785548}, {"type": "node", "id": 6003392267, "lat": 53.4074203, "lon": -2.9785663}, {"type": "node", "id": 6003392270, "lat": 53.4074397, "lon": -2.9757032}, {"type": "node", "id": 6003392271, "lat": 53.4075019, "lon": -2.9755353}, {"type": "node", "id": 6003392272, "lat": 53.407483, "lon": -2.9755449}, {"type": "node", "id": 6003392273, "lat": 53.4080657, "lon": -2.9779885}, {"type": "node", "id": 6003392274, "lat": 53.4076866, "lon": -2.9759304}, {"type": "node", "id": 6003392275, "lat": 53.4075762, "lon": -2.9753402}, {"type": "node", "id": 6003392276, "lat": 53.4074639, "lon": -2.9746162}, {"type": "node", "id": 6003392277, "lat": 53.4074266, "lon": -2.9746317}, {"type": "node", "id": 6003392278, "lat": 53.4079543, "lon": -2.9780401}, {"type": "node", "id": 6003392279, "lat": 53.4075867, "lon": -2.9760097}, {"type": "node", "id": 6003536980, "lat": 53.4078276, "lon": -2.977905, "tags": {"name": "Liverpool Lime Street", "public_transport": "stop_position", "railway": "stop", "ref": "5", "train": "yes"}}, {"type": "node", "id": 6003536981, "lat": 53.4078559, "lon": -2.9778884, "tags": {"name": "Liverpool Lime Street", "public_transport": "stop_position", "railway": "stop", "ref": "4", "train": "yes"}}, {"type": "node", "id": 6003536982, "lat": 53.4079681, "lon": -2.9778379, "tags": {"name": "Liverpool Lime Street", "public_transport": "stop_position", "railway": "stop", "ref": "2", "train": "yes"}}, {"type": "node", "id": 6003536983, "lat": 53.4079392, "lon": -2.9778505, "tags": {"name": "Liverpool Lime Street", "public_transport": "stop_position", "railway": "stop", "ref": "3", "train": "yes"}}, {"type": "node", "id": 6003537493, "lat": 53.4081316, "lon": -2.977955}, {"type": "node", "id": 6003537494, "lat": 53.4076582, "lon": -2.9755276}, {"type": "node", "id": 6003537495, "lat": 53.4076271, "lon": -2.9753983}, {"type": "node", "id": 6004512611, "lat": 53.4081539, "lon": -2.9779441}, {"type": "node", "id": 6004512615, "lat": 53.4079324, "lon": -2.9780498}, {"type": "node", "id": 6004512617, "lat": 53.4073374, "lon": -2.9785975}, {"type": "node", "id": 6004512619, "lat": 53.4074563, "lon": -2.9785824}, {"type": "node", "id": 6004512621, "lat": 53.407579, "lon": -2.978567}, {"type": "node", "id": 6004512624, "lat": 53.4073804, "lon": -2.9753665}, {"type": "node", "id": 6004512625, "lat": 53.4070924, "lon": -2.974595}, {"type": "node", "id": 6004512626, "lat": 53.4070746, "lon": -2.9768045}, {"type": "node", "id": 6004512627, "lat": 53.4071076, "lon": -2.9772467}, {"type": "node", "id": 6004512628, "lat": 53.4071443, "lon": -2.9775403}, {"type": "node", "id": 6004512629, "lat": 53.4073138, "lon": -2.9786079}, {"type": "node", "id": 6004512630, "lat": 53.4073564, "lon": -2.9785895}, {"type": "node", "id": 6004512631, "lat": 53.4071399, "lon": -2.977143}, {"type": "node", "id": 6004512632, "lat": 53.40711, "lon": -2.9767208}, {"type": "node", "id": 6004512633, "lat": 53.4070984, "lon": -2.9762996}, {"type": "node", "id": 6004512634, "lat": 53.4071188, "lon": -2.9745984}, {"type": "node", "id": 6004512638, "lat": 53.4075173, "lon": -2.977573}, {"type": "node", "id": 6004512640, "lat": 53.4074645, "lon": -2.9776289}, {"type": "node", "id": 6004512641, "lat": 53.4073923, "lon": -2.9776032}, {"type": "node", "id": 6004512644, "lat": 53.4073261, "lon": -2.977579}, {"type": "node", "id": 6004512645, "lat": 53.40738, "lon": -2.978426, "tags": {"name": "Liverpool Lime Street", "public_transport": "stop_position", "railway": "stop", "ref": "9", "train": "yes"}}, {"type": "node", "id": 6004512646, "lat": 53.4074835, "lon": -2.9784514, "tags": {"name": "Liverpool Lime Street", "public_transport": "stop_position", "railway": "stop", "ref": "8", "train": "yes"}}, {"type": "node", "id": 6004512647, "lat": 53.4075107, "lon": -2.9784401, "tags": {"name": "Liverpool Lime Street", "public_transport": "stop_position", "railway": "stop", "ref": "7", "train": "yes"}}, {"type": "node", "id": 6004512652, "lat": 53.4072014, "lon": -2.9771267}, {"type": "node", "id": 6004512654, "lat": 53.4072485, "lon": -2.9775022}, {"type": "node", "id": 6004512655, "lat": 53.4074919, "lon": -2.9785992}, {"type": "node", "id": 6004512656, "lat": 53.4072752, "lon": -2.9771827}, {"type": "node", "id": 6004512657, "lat": 53.4072537, "lon": -2.9769686}, {"type": "node", "id": 6004512658, "lat": 53.4072308, "lon": -2.9767156}, {"type": "node", "id": 6004512659, "lat": 53.4072152, "lon": -2.976457}, {"type": "node", "id": 6004512661, "lat": 53.4071808, "lon": -2.9756102}, {"type": "node", "id": 6004512662, "lat": 53.4071891, "lon": -2.9752395}, {"type": "node", "id": 6004512663, "lat": 53.4072116, "lon": -2.9748506}, {"type": "node", "id": 6004512664, "lat": 53.4075495, "lon": -2.9785793}, {"type": "node", "id": 6004512665, "lat": 53.4073343, "lon": -2.9771548}, {"type": "node", "id": 6004512666, "lat": 53.4072961, "lon": -2.9767551}, {"type": "node", "id": 6004512667, "lat": 53.4072732, "lon": -2.9764354}, {"type": "node", "id": 6004512668, "lat": 53.4072649, "lon": -2.9762243}, {"type": "node", "id": 6004512672, "lat": 53.4072818, "lon": -2.9750772}, {"type": "node", "id": 6004512673, "lat": 53.4072544, "lon": -2.9747439}, {"type": "node", "id": 6004512674, "lat": 53.4072547, "lon": -2.9746034}, {"type": "node", "id": 6004512675, "lat": 53.4072502, "lon": -2.9745122}, {"type": "node", "id": 6109282163, "lat": 53.4079265, "lon": -2.9802162, "tags": {"entrance": "yes", "name": "Lime Street Low Level", "railway": "subway_entrance", "source": "survey", "wheelchair": "yes"}}, {"type": "node", "id": 6109282171, "lat": 53.4079384, "lon": -2.9801403, "tags": {"entrance": "yes", "name": "Lime Street Low Level", "railway": "subway_entrance"}}, {"type": "node", "id": 6109340302, "lat": 53.409069, "lon": -2.98021}, {"type": "node", "id": 6109340303, "lat": 53.4087856, "lon": -2.9796043}, {"type": "node", "id": 6109340306, "lat": 53.4084015, "lon": -2.9787682}, {"type": "node", "id": 6120201602, "lat": 53.4084151, "lon": -2.9787983}, {"type": "node", "id": 6120201617, "lat": 53.4080953, "lon": -2.9788168, "tags": {"railway": "subway_entrance", "wheelchair": "yes"}}, {"type": "node", "id": 6120201618, "lat": 53.4076822, "lon": -2.9783539}, {"type": "node", "id": 6120201638, "lat": 53.4072322, "lon": -2.9780901}, {"type": "node", "id": 6120228655, "lat": 53.4078219, "lon": -2.9781002}, {"type": "node", "id": 6120228656, "lat": 53.4073059, "lon": -2.9764266}, {"type": "node", "id": 6120228657, "lat": 53.407359, "lon": -2.9770793}, {"type": "node", "id": 6120228658, "lat": 53.407796, "lon": -2.9781126}, {"type": "node", "id": 6120228661, "lat": 53.4075673, "lon": -2.9760146}, {"type": "node", "id": 6120228662, "lat": 53.4073967, "lon": -2.9759948}, {"type": "node", "id": 6120228663, "lat": 53.407664, "lon": -2.9759411}, {"type": "node", "id": 6120228665, "lat": 53.4080422, "lon": -2.9779995}, {"type": "node", "id": 6120228666, "lat": 53.4074244, "lon": -2.9775941}, {"type": "node", "id": 6120228667, "lat": 53.4070605, "lon": -2.9762455}, {"type": "node", "id": 6120228669, "lat": 53.4078929, "lon": -2.9771891}, {"type": "node", "id": 6120228670, "lat": 53.4072823, "lon": -2.9774912}, {"type": "node", "id": 6120228671, "lat": 53.4071455, "lon": -2.9759973}, {"type": "node", "id": 6120228672, "lat": 53.4075457, "lon": -2.9766358}, {"type": "node", "id": 6120228673, "lat": 53.4074445, "lon": -2.9746228}, {"type": "node", "id": 6120228676, "lat": 53.4075574, "lon": -2.9753529}, {"type": "node", "id": 6120228677, "lat": 53.4074531, "lon": -2.9760299}, {"type": "node", "id": 6120228678, "lat": 53.4071865, "lon": -2.9764386}, {"type": "node", "id": 6120228679, "lat": 53.4071825, "lon": -2.9774939}, {"type": "node", "id": 6120228680, "lat": 53.4074917, "lon": -2.9755406}, {"type": "node", "id": 6120228681, "lat": 53.4074215, "lon": -2.9756827}, {"type": "node", "id": 6120228682, "lat": 53.4072358, "lon": -2.9771349}, {"type": "node", "id": 6120228684, "lat": 53.4071788, "lon": -2.9759792}, {"type": "node", "id": 6121214733, "lat": 53.4078264, "lon": -2.9782883}, {"type": "node", "id": 6123978483, "lat": 53.4070881, "lon": -2.9757546}, {"type": "node", "id": 6123978587, "lat": 53.4070679, "lon": -2.9757767}, {"type": "node", "id": 6142534100, "lat": 53.4085892, "lon": -2.9791851}, {"type": "node", "id": 6143005204, "lat": 53.4070627, "lon": -2.9764047}, {"type": "node", "id": 6144708865, "lat": 53.4072097, "lon": -2.9768299}, {"type": "node", "id": 6175652825, "lat": 53.4073103, "lon": -2.9832583}, {"type": "node", "id": 6175652836, "lat": 53.4072631, "lon": -2.9829049}, {"type": "node", "id": 6190860246, "lat": 53.4072065, "lon": -2.9762229}, {"type": "node", "id": 6190860248, "lat": 53.4073052, "lon": -2.9762245}, {"type": "node", "id": 6190860250, "lat": 53.4071817, "lon": -2.9762231}, {"type": "node", "id": 6960405293, "lat": 53.4076085, "lon": -2.9775854, "tags": {"addr:city": "Liverpool", "addr:postcode": "L1 1JD", "addr:street": "Lime Street", "alt_name": "LIVERPOOL LIME STREET LL", "name": "Liverpool Lime Street", "name:ko": "\ub9ac\ubc84\ud480 \ub77c\uc784 \uc2a4\ud2b8\ub9ac\ud2b8 \uc5ed", "naptan:AtcoCode": "9100LVRPLSH", "network": "National Rail", "network:website": "https://www.nationalrail.co.uk/stations/liv/", "network:wikidata": "Q26334", "operator": "Network Rail", "public_transport": "station", "railway": "station", "ref:alt_crs": "LVL", "ref:crs": "LIV", "train": "yes", "wheelchair": "yes", "wikidata": "Q801113", "wikipedia": "en:Liverpool Lime Street railway station"}}, {"type": "node", "id": 8079171222, "lat": 53.4120508, "lon": -2.9813454, "tags": {"addr:city": "Liverpool", "addr:postcode": "L3 3AF", "addr:street": "Byrom Street", "name": "John Moores Students' Union (JMSU) - Byrom Street", "name:ja": "\u30b8\u30e7\u30f3\u30fb\u30e0\u30fc\u30a2\u5b66\u751f\u30e6\u30cb\u30aa\u30f3(\u30ea\u30f4\u30a1\u30d7\u30fc\u30eb\u30fb\u30b8\u30e7\u30f3\u30fb\u30e0\u30fc\u30a2\u5927\u5b66) - \u30d0\u30a4\u30ed\u30e0\u901a\u308a", "office": "yes", "website": "https://www.jmsu.co.uk/"}}, {"type": "node", "id": 8079171224, "lat": 53.4122804, "lon": -2.9814947, "tags": {"addr:city": "Liverpool", "addr:postcode": "L3 3AF", "addr:street": "Byrom Street", "name": "Careers Zone Byrom Street", "office": "yes"}}, {"type": "node", "id": 8129883502, "lat": 53.4083204, "lon": -2.9793208, "tags": {"bus": "yes", "highway": "bus_stop", "name": "LIME ST RAIL STATION", "naptan:AtcoCode": "2800S42024B", "naptan:Bearing": "N", "naptan:CommonName": "St Georges Hall", "naptan:Indicator": "Outside", "naptan:Landmark": "NR EMPIRE THEATRE", "naptan:NaptanCode": "mertwpwt", "naptan:Notes": "No Notes", "naptan:PlusbusZoneRef": "LVRPLCH", "naptan:ShortCommonName": "Lime St Station", "naptan:Street": "Lime Street", "naptan:verified": "no", "public_transport": "platform", "source": "naptan_import", "wheelchair": "yes"}}, {"type": "node", "id": 8129883503, "lat": 53.4103581, "lon": -2.9782726}, {"type": "node", "id": 8250225742, "lat": 53.4104317, "lon": -2.9778212}, {"type": "node", "id": 8250225744, "lat": 53.4104394, "lon": -2.9783292}, {"type": "node", "id": 8250225745, "lat": 53.4104336, "lon": -2.9783483}, {"type": "node", "id": 8297295315, "lat": 53.40775, "lon": -2.9757365}, {"type": "node", "id": 8297295316, "lat": 53.4076906, "lon": -2.975524}, {"type": "node", "id": 8297307517, "lat": 53.4077717, "lon": -2.9760244}, {"type": "node", "id": 8297307518, "lat": 53.4077212, "lon": -2.9756244}, {"type": "node", "id": 8297307519, "lat": 53.407813, "lon": -2.9760322}, {"type": "node", "id": 8297556557, "lat": 53.4072643, "lon": -2.9750109}, {"type": "node", "id": 8297556558, "lat": 53.4075268, "lon": -2.975834}, {"type": "node", "id": 8297556561, "lat": 53.4074059, "lon": -2.9757952}, {"type": "node", "id": 8297556563, "lat": 53.4075094, "lon": -2.9755795}, {"type": "node", "id": 8297556564, "lat": 53.4075215, "lon": -2.9755944}, {"type": "node", "id": 8297556567, "lat": 53.4073919, "lon": -2.9755009}, {"type": "node", "id": 8297556569, "lat": 53.4073757, "lon": -2.9753686}, {"type": "node", "id": 8297556572, "lat": 53.4070862, "lon": -2.9759738}, {"type": "node", "id": 8297556574, "lat": 53.4073947, "lon": -2.9757959}, {"type": "node", "id": 8926457547, "lat": 53.4125835, "lon": -2.9826732, "tags": {"bus": "yes", "highway": "bus_stop", "public_transport": "platform"}}, {"type": "node", "id": 9543046197, "lat": 53.4075488, "lon": -2.9825767}, {"type": "node", "id": 9543046198, "lat": 53.4075656, "lon": -2.9823661}, {"type": "node", "id": 9543046199, "lat": 53.4079461, "lon": -2.9814689}, {"type": "node", "id": 9543046200, "lat": 53.4077685, "lon": -2.9812096}, {"type": "node", "id": 9543046201, "lat": 53.4073888, "lon": -2.9838719}, {"type": "node", "id": 9543046202, "lat": 53.4074065, "lon": -2.9839404}, {"type": "node", "id": 10702635597, "lat": 53.40781, "lon": -2.9787764}, {"type": "node", "id": 10702635598, "lat": 53.4077979, "lon": -2.9785617}, {"type": "node", "id": 10702635599, "lat": 53.4078676, "lon": -2.9785309}, {"type": "node", "id": 10702635600, "lat": 53.4078975, "lon": -2.978735}, {"type": "node", "id": 10702669609, "lat": 53.4079468, "lon": -2.9783523}, {"type": "node", "id": 10702669610, "lat": 53.4078431, "lon": -2.9783962}, {"type": "node", "id": 10702669618, "lat": 53.407811, "lon": -2.9784102}, {"type": "node", "id": 10702669619, "lat": 53.4077943, "lon": -2.9783023}, {"type": "node", "id": 10702669621, "lat": 53.4077641, "lon": -2.9783164}, {"type": "node", "id": 10702669622, "lat": 53.4077383, "lon": -2.9783282}, {"type": "node", "id": 10702669624, "lat": 53.4079381, "lon": -2.9782983}, {"type": "node", "id": 10873837613, "lat": 53.4077553, "lon": -2.9831199}, {"type": "node", "id": 10873837616, "lat": 53.4078494, "lon": -2.9829463}, {"type": "node", "id": 10873837617, "lat": 53.4078467, "lon": -2.9829497}, {"type": "node", "id": 10873837620, "lat": 53.407845, "lon": -2.9832831}, {"type": "node", "id": 10873837621, "lat": 53.4079518, "lon": -2.9830085}, {"type": "node", "id": 10912583288, "lat": 53.4095458, "lon": -2.9770749}, {"type": "node", "id": 10912583289, "lat": 53.4095567, "lon": -2.9770765}, {"type": "node", "id": 10912583290, "lat": 53.4095618, "lon": -2.9769774}, {"type": "node", "id": 10912583291, "lat": 53.4094008, "lon": -2.9770008}, {"type": "node", "id": 10912583294, "lat": 53.4094881, "lon": -2.977082}, {"type": "node", "id": 10912583295, "lat": 53.4094033, "lon": -2.9770764}, {"type": "node", "id": 10912583296, "lat": 53.4094879, "lon": -2.9770705}, {"type": "node", "id": 10913976274, "lat": 53.4092262, "lon": -2.9764735}, {"type": "node", "id": 10913976275, "lat": 53.4091296, "lon": -2.976476}, {"type": "node", "id": 10913976276, "lat": 53.4092234, "lon": -2.9762206}, {"type": "node", "id": 10913976277, "lat": 53.4091305, "lon": -2.9762262}, {"type": "node", "id": 10913976278, "lat": 53.4091318, "lon": -2.9762651}, {"type": "node", "id": 10913976279, "lat": 53.4092206, "lon": -2.9761352}, {"type": "node", "id": 10913976280, "lat": 53.409129, "lon": -2.9761438}, {"type": "node", "id": 10913976283, "lat": 53.4092183, "lon": -2.9760735}, {"type": "node", "id": 10913976284, "lat": 53.4091356, "lon": -2.9760788}, {"type": "node", "id": 10913976285, "lat": 53.4091376, "lon": -2.9761245}, {"type": "node", "id": 10913976286, "lat": 53.4091283, "lon": -2.976126}, {"type": "node", "id": 10913976287, "lat": 53.4091297, "lon": -2.9759747}, {"type": "node", "id": 10913976290, "lat": 53.4094527, "lon": -2.9761262}, {"type": "node", "id": 10913976291, "lat": 53.4094531, "lon": -2.9761087}, {"type": "node", "id": 10913976292, "lat": 53.4093832, "lon": -2.9761047}, {"type": "node", "id": 10913976293, "lat": 53.4093857, "lon": -2.975864}, {"type": "node", "id": 10913976294, "lat": 53.4094543, "lon": -2.9758639}, {"type": "node", "id": 10913976295, "lat": 53.409454, "lon": -2.9759399}, {"type": "node", "id": 10913976296, "lat": 53.409385, "lon": -2.9759391}, {"type": "node", "id": 10913979906, "lat": 53.408655, "lon": -2.9777541}, {"type": "node", "id": 10913979913, "lat": 53.4095109, "lon": -2.9774967}, {"type": "node", "id": 10913979914, "lat": 53.4095342, "lon": -2.9754179}, {"type": "node", "id": 10913979915, "lat": 53.4093877, "lon": -2.975414}, {"type": "node", "id": 10913979916, "lat": 53.4093886, "lon": -2.9753118}, {"type": "node", "id": 10913979917, "lat": 53.4095352, "lon": -2.9753157}, {"type": "node", "id": 10944259365, "lat": 53.4094051, "lon": -2.9739779}, {"type": "node", "id": 10944259366, "lat": 53.4095899, "lon": -2.9740821}, {"type": "node", "id": 10944259369, "lat": 53.4094168, "lon": -2.9737585}, {"type": "node", "id": 11073213293, "lat": 53.4075694, "lon": -2.9818011, "tags": {"bus": "yes", "name": "Queens Square (Alighting only)", "public_transport": "stop_position"}}, {"type": "node", "id": 11449842683, "lat": 53.4073144, "lon": -2.982372}, {"type": "node", "id": 12157768492, "lat": 53.4075137, "lon": -2.9828303}, {"type": "node", "id": 12157768493, "lat": 53.4075141, "lon": -2.9828137}, {"type": "node", "id": 12157768494, "lat": 53.4075203, "lon": -2.9827995}, {"type": "node", "id": 12157768495, "lat": 53.4075274, "lon": -2.9827933}, {"type": "node", "id": 12157768496, "lat": 53.4075352, "lon": -2.9827921}, {"type": "node", "id": 12157768497, "lat": 53.4075447, "lon": -2.9827979}, {"type": "node", "id": 12157768498, "lat": 53.4075502, "lon": -2.9828079}, {"type": "node", "id": 12157768499, "lat": 53.4075674, "lon": -2.9829265}, {"type": "node", "id": 12157768500, "lat": 53.4075708, "lon": -2.9829523}, {"type": "node", "id": 12157805891, "lat": 53.4076311, "lon": -2.9837936}, {"type": "node", "id": 12157815001, "lat": 53.4075697, "lon": -2.9829662}, {"type": "node", "id": 12157815002, "lat": 53.407563, "lon": -2.9829751}, {"type": "node", "id": 12157815003, "lat": 53.4075561, "lon": -2.9829766}, {"type": "node", "id": 12157815004, "lat": 53.4075511, "lon": -2.9829731}, {"type": "node", "id": 12157815005, "lat": 53.4075489, "lon": -2.9830931}, {"type": "node", "id": 12157815006, "lat": 53.4075494, "lon": -2.9830766}, {"type": "node", "id": 12157815007, "lat": 53.4075556, "lon": -2.9830623}, {"type": "node", "id": 12157815008, "lat": 53.4075627, "lon": -2.9830561}, {"type": "node", "id": 12157815009, "lat": 53.4075705, "lon": -2.983055}, {"type": "node", "id": 12157815010, "lat": 53.4075799, "lon": -2.9830608}, {"type": "node", "id": 12157815011, "lat": 53.4075854, "lon": -2.9830708}, {"type": "node", "id": 12157815012, "lat": 53.4076026, "lon": -2.9831894}, {"type": "node", "id": 12157815013, "lat": 53.4076061, "lon": -2.9832152}, {"type": "node", "id": 12157815014, "lat": 53.4076049, "lon": -2.9832291}, {"type": "node", "id": 12157815015, "lat": 53.4075983, "lon": -2.9832379}, {"type": "node", "id": 12157815016, "lat": 53.4075914, "lon": -2.9832395}, {"type": "node", "id": 12157815017, "lat": 53.4075863, "lon": -2.983236}, {"type": "node", "id": 12157815031, "lat": 53.4074764, "lon": -2.9825663}, {"type": "node", "id": 12157815032, "lat": 53.4074768, "lon": -2.9825497}, {"type": "node", "id": 12157815033, "lat": 53.407483, "lon": -2.9825354}, {"type": "node", "id": 12157815034, "lat": 53.4074901, "lon": -2.9825293}, {"type": "node", "id": 12157815035, "lat": 53.4074979, "lon": -2.9825281}, {"type": "node", "id": 12157815036, "lat": 53.4075074, "lon": -2.9825339}, {"type": "node", "id": 12157815037, "lat": 53.4075129, "lon": -2.9825439}, {"type": "node", "id": 12157815038, "lat": 53.4075301, "lon": -2.9826625}, {"type": "node", "id": 12157815039, "lat": 53.4075335, "lon": -2.9826883}, {"type": "node", "id": 12157815040, "lat": 53.4075324, "lon": -2.9827022}, {"type": "node", "id": 12157815041, "lat": 53.4075257, "lon": -2.9827111}, {"type": "node", "id": 12157815042, "lat": 53.4075188, "lon": -2.9827126}, {"type": "node", "id": 12157815043, "lat": 53.4075138, "lon": -2.9827091}, {"type": "node", "id": 12157815044, "lat": 53.4076116, "lon": -2.9820373}, {"type": "node", "id": 12157815045, "lat": 53.4076188, "lon": -2.9820259}, {"type": "node", "id": 12157815046, "lat": 53.4076292, "lon": -2.9820229}, {"type": "node", "id": 12157815047, "lat": 53.4076369, "lon": -2.9820267}, {"type": "node", "id": 12157815048, "lat": 53.407643, "lon": -2.982035}, {"type": "node", "id": 12157815049, "lat": 53.4076473, "lon": -2.9820501}, {"type": "node", "id": 12157815050, "lat": 53.4076471, "lon": -2.9820637}, {"type": "node", "id": 12157815051, "lat": 53.4076104, "lon": -2.9821691}, {"type": "node", "id": 12157815052, "lat": 53.4076022, "lon": -2.9821917}, {"type": "node", "id": 12157815053, "lat": 53.4075956, "lon": -2.9822003}, {"type": "node", "id": 12157815054, "lat": 53.4075872, "lon": -2.9821989}, {"type": "node", "id": 12157815055, "lat": 53.4075816, "lon": -2.982192}, {"type": "node", "id": 12157815056, "lat": 53.4075794, "lon": -2.9821836}, {"type": "node", "id": 12157815057, "lat": 53.4077075, "lon": -2.9818192}, {"type": "node", "id": 12157815058, "lat": 53.4077147, "lon": -2.9818078}, {"type": "node", "id": 12157815059, "lat": 53.4077251, "lon": -2.9818048}, {"type": "node", "id": 12157815060, "lat": 53.4077327, "lon": -2.9818086}, {"type": "node", "id": 12157815061, "lat": 53.4077388, "lon": -2.9818169}, {"type": "node", "id": 12157815062, "lat": 53.4077432, "lon": -2.981832}, {"type": "node", "id": 12157815063, "lat": 53.407743, "lon": -2.9818457}, {"type": "node", "id": 12157815064, "lat": 53.4077063, "lon": -2.981951}, {"type": "node", "id": 12157815065, "lat": 53.4076981, "lon": -2.9819736}, {"type": "node", "id": 12157815066, "lat": 53.4076915, "lon": -2.9819822}, {"type": "node", "id": 12157815067, "lat": 53.4076831, "lon": -2.9819809}, {"type": "node", "id": 12157815068, "lat": 53.4076775, "lon": -2.9819739}, {"type": "node", "id": 12157815069, "lat": 53.4076753, "lon": -2.9819656}, {"type": "node", "id": 12157815070, "lat": 53.407798, "lon": -2.9815915}, {"type": "node", "id": 12157815071, "lat": 53.4078052, "lon": -2.9815801}, {"type": "node", "id": 12157815072, "lat": 53.4078155, "lon": -2.9815771}, {"type": "node", "id": 12157815073, "lat": 53.4078232, "lon": -2.981581}, {"type": "node", "id": 12157815074, "lat": 53.4078293, "lon": -2.9815892}, {"type": "node", "id": 12157815075, "lat": 53.4078337, "lon": -2.9816044}, {"type": "node", "id": 12157815076, "lat": 53.4078335, "lon": -2.981618}, {"type": "node", "id": 12157815077, "lat": 53.4077968, "lon": -2.9817234}, {"type": "node", "id": 12157815078, "lat": 53.4077886, "lon": -2.981746}, {"type": "node", "id": 12157815079, "lat": 53.407782, "lon": -2.9817546}, {"type": "node", "id": 12157815080, "lat": 53.4077735, "lon": -2.9817532}, {"type": "node", "id": 12157815081, "lat": 53.4077679, "lon": -2.9817463}, {"type": "node", "id": 12157815082, "lat": 53.4077657, "lon": -2.9817379}, {"type": "node", "id": 12157815083, "lat": 53.407892, "lon": -2.9813697}, {"type": "node", "id": 12157815084, "lat": 53.4078991, "lon": -2.9813583}, {"type": "node", "id": 12157815085, "lat": 53.4079095, "lon": -2.9813553}, {"type": "node", "id": 12157815086, "lat": 53.4079172, "lon": -2.9813592}, {"type": "node", "id": 12157815087, "lat": 53.4079233, "lon": -2.9813674}, {"type": "node", "id": 12157815088, "lat": 53.4079276, "lon": -2.9813825}, {"type": "node", "id": 12157815089, "lat": 53.4079275, "lon": -2.9813962}, {"type": "node", "id": 12157815090, "lat": 53.4078907, "lon": -2.9815016}, {"type": "node", "id": 12157815091, "lat": 53.4078825, "lon": -2.9815241}, {"type": "node", "id": 12157815092, "lat": 53.4078759, "lon": -2.9815328}, {"type": "node", "id": 12157815093, "lat": 53.4078675, "lon": -2.9815314}, {"type": "node", "id": 12157815094, "lat": 53.4078619, "lon": -2.9815245}, {"type": "node", "id": 12157815095, "lat": 53.4078597, "lon": -2.9815161}, {"type": "node", "id": 12157815096, "lat": 53.4079092, "lon": -2.9813454}, {"type": "node", "id": 12157822824, "lat": 53.4077706, "lon": -2.9817065, "tags": {"barrier": "bollard"}}, {"type": "node", "id": 12157825303, "lat": 53.4074765, "lon": -2.982563}, {"type": "node", "id": 12157825315, "lat": 53.4077362, "lon": -2.9818133}, {"type": "node", "id": 12157837049, "lat": 53.407606, "lon": -2.9822836}, {"type": "node", "id": 12157837050, "lat": 53.407948, "lon": -2.9813918}, {"type": "node", "id": 12157837051, "lat": 53.407966, "lon": -2.981436}, {"type": "node", "id": 12864361944, "lat": 53.4076593, "lon": -2.9817532, "tags": {"bus": "yes", "name": "Liverpool Queen Square (Stand 6)", "public_transport": "stop_position"}}, {"type": "node", "id": 12866349803, "lat": 53.4075584, "lon": -2.9819931, "tags": {"bus": "yes", "name": "Liverpool Queen Square (Stand 5)", "public_transport": "stop_position"}}, {"type": "node", "id": 12954017615, "lat": 53.4074808, "lon": -2.9831329, "tags": {"bus": "yes", "name": "Liverpool Queen Square (Stand 2)", "public_transport": "stop_position"}}, {"type": "node", "id": 13112626888, "lat": 53.4077566, "lon": -2.9815273, "tags": {"bus": "yes", "name": "Liverpool Queen Sqaure (Stand 7)", "public_transport": "stop_position"}}, {"type": "node", "id": 13197439204, "lat": 53.4074405, "lon": -2.9828387, "tags": {"bus": "yes", "name": "Liverpool Queen Square (Stand 3)", "public_transport": "stop_position"}}, {"type": "node", "id": 13801307781, "lat": 53.4085479, "lon": -2.9777159}, {"type": "node", "id": 13801307782, "lat": 53.4086022, "lon": -2.9777044}, {"type": "node", "id": 13801307783, "lat": 53.4085988, "lon": -2.9776625}, {"type": "node", "id": 13801307786, "lat": 53.408607, "lon": -2.9776608}, {"type": "way", "id": 42739141, "nodes": [6120228673, 6003392277, 2462951415, 534436303, 534436305, 6120228665, 6120228669, 6120228663, 6120228676, 6120228673], "tags": {"area": "yes", "bench": "yes", "covered": "yes", "public_transport": "platform", "railway": "platform", "ref": "2"}}, {"type": "way", "id": 42739145, "nodes": [6120228680, 6003392272, 8297556558, 534436324, 534436326, 2462951475, 6004512615, 6120228661, 6120228680], "tags": {"area": "yes", "bench": "yes", "public_transport": "platform", "railway": "platform", "ref": "4", "shelter": "yes"}}, {"type": "way", "id": 42739291, "nodes": [6190860248, 6120228656, 6120228657, 6120228666, 6004512621, 6004512664, 6004512641, 6004512665, 6004512666, 6004512667, 6004512668, 6190860248], "tags": {"area": "yes", "bench": "yes", "bin": "no", "lit": "yes", "public_transport": "platform", "railway": "platform", "ref": "7", "shelter": "yes", "tactile_paving": "yes"}}, {"type": "way", "id": 199267548, "nodes": [2092815588, 2092815578, 2092815579, 2092815590, 2092815588], "tags": {"addr:city": "Liverpool", "addr:housenumber": "24", "addr:street": "Norton Street", "building": "yes", "name": "LJMU Tower", "office": "university", "source": "bing"}}, {"type": "way", "id": 213185600, "nodes": [2702384791, 13801307781, 13801307782, 13801307783, 13801307786, 4417907637, 10913979906, 2229242045, 2702384791], "tags": {"addr:city": "Liverpool", "addr:housenumber": "9", "addr:postcode": "L1 1JA", "addr:street": "Pudsey Street", "amenity": "pub", "building": "retail", "building:levels": "3", "fhrs:id": "499059", "name": "Ma Egertons", "phone": "+44 151 345 3525", "real_ale": "2 beers, may vary", "website": "https://www.maegertons.com/", "wheelchair": "limited", "wheelchair:description": "Small step at entrance"}}, {"type": "way", "id": 238460783, "nodes": [6120228658, 6121214733, 10702669619, 10702669621, 10702669622, 6120201618, 1021462427, 6004512638, 2462951520, 2462951516, 2462951527, 6120228662, 8297556574, 8297556561, 8297556567, 8297556569, 6004512624, 6120228681, 6120228677, 6120228672, 6120228658], "tags": {"access": "private", "area": "yes", "bench": "yes", "public_transport": "platform", "railway": "platform", "shelter": "yes", "tactile_paving": "no"}}, {"type": "way", "id": 238460801, "nodes": [534436267, 534436269, 8297307519, 8297295315, 8297307518, 8297295316, 534436270, 6003537495, 6003537494, 8297307517, 6003537493, 6004512611, 534436267], "tags": {"access": "private", "area": "yes", "public_transport": "platform", "railway": "platform"}}, {"type": "way", "id": 271759719, "nodes": [2767005085, 10913979915, 10913979916, 2767005246, 2767005203, 10913979917, 10913979914, 2767005166, 2767005112, 2767005085], "tags": {"building": "yes", "name": "Gateway Conference Centre", "office": "yes"}}, {"type": "way", "id": 271759731, "nodes": [2767005100, 2767005212, 2767005201, 10913979913, 2767005188, 2767005100], "tags": {"addr:city": "Liverpool", "addr:housenumber": "21", "addr:postcode": "L3 8HR", "addr:street": "London Road", "amenity": "pub", "building": "retail", "fhrs:id": "1709197", "name": "Sketch", "source": "survey", "source:addr": "FHRS Open Data", "source:geometry": "Bing"}}, {"type": "way", "id": 271759734, "nodes": [2767005078, 2767005209, 2767005158, 2767005081, 2767005118, 2767005257, 2767005122, 2767005075, 2767005153, 2767005168, 2767005180, 2767005174, 2767005247, 2767005113, 2767005151, 2767005078], "tags": {"addr:city": "Liverpool", "addr:postcode": "L3 8LR", "addr:street": "Norton Street", "building": "yes", "name": "The Brain Charity", "office": "charity", "website": "https://www.thebraincharity.org.uk/"}}, {"type": "way", "id": 271759848, "nodes": [2767006378, 2767006381, 2767006382, 2767006370, 2767006374, 8250225744, 8250225745, 8129883503, 2767006373, 2767006369, 2767006376, 8250225742, 2767006377, 2767006371, 2767006383, 2767006379, 2767006372, 2767006378], "tags": {"building": "yes", "office": "yes"}}, {"type": "way", "id": 444302600, "nodes": [4417907638, 4417907450, 4417907644, 4417907627, 4417907638], "tags": {"amenity": "pharmacy", "brand": "Boots", "brand:wikidata": "Q6123139", "brand:wikipedia": "en:Boots (company)", "building": "yes", "building:levels": "3", "healthcare": "pharmacy", "name": "Boots"}}, {"type": "way", "id": 444302624, "nodes": [4417907644, 4417907639, 4417907466, 4417907450, 4417907644], "tags": {"addr:city": "Liverpool", "addr:housenumber": "64 - 66", "addr:postcode": "L3 5NF", "addr:street": "London Road", "brand": "Best-one", "brand:wikidata": "Q4896532", "building": "retail", "building:levels": "3", "fhrs:id": "1243577", "name": "Best-one", "shop": "convenience", "source:addr": "FHRS Open Data"}}, {"type": "way", "id": 444302626, "nodes": [4417907480, 4417914225, 4417907610, 4417907599, 4417907480], "tags": {"addr:city": "Liverpool", "addr:street": "London Road", "amenity": "restaurant", "building": "yes", "building:levels": "4", "cuisine": "kurdish", "name": "Lazeez Kurdish Charcoal Grill Restaurant"}}, {"type": "way", "id": 636797800, "nodes": [6004512634, 6123978483, 8297556572, 6004512633, 6004512632, 6004512631, 6120228679, 6004512630, 6004512617, 6004512629, 6120201638, 6004512628, 6004512627, 6004512626, 6143005204, 6120228667, 6123978587, 6004512625, 6004512634], "tags": {"area": "yes", "bench": "yes", "bin": "no", "lit": "yes", "public_transport": "platform", "railway": "platform", "ref": "10", "shelter": "yes"}}, {"type": "way", "id": 636797807, "nodes": [6004512619, 6003392267, 6004512654, 6004512652, 534438316, 2462953568, 6120228671, 6003392253, 6003392254, 6004512663, 6004512662, 6004512661, 6120228684, 6190860250, 6120228678, 6144708865, 6120228682, 6120228670, 6004512619], "tags": {"area": "yes", "bench": "yes", "bin": "no", "lit": "yes", "public_transport": "platform", "railway": "platform", "ref": "9", "shelter": "yes"}}, {"type": "way", "id": 651521416, "nodes": [6109340302, 6109340303, 6142534100, 6120201602, 6109340306], "tags": {"layer": "-3", "level": "-3", "name": "A", "public_transport": "platform", "railway": "platform", "ref": "A", "source": "SE end from lift access, length for 6 car train is 120m", "train": "yes", "underground": "yes", "wheelchair": "yes"}}, {"type": "way", "id": 652977980, "nodes": [6120228665, 6003392273, 6003392274, 6003392275, 6003392276, 6120228673, 6120228676, 6120228663, 6120228669, 6120228665], "tags": {"area": "yes", "bench": "yes", "public_transport": "platform", "railway": "platform", "ref": "1", "shelter": "yes"}}, {"type": "way", "id": 652977985, "nodes": [6004512615, 6003392278, 6003392279, 8297556564, 8297556563, 6003392271, 6120228680, 6120228661, 6004512615], "tags": {"area": "yes", "bench": "yes", "public_transport": "platform", "railway": "platform", "ref": "3", "shelter": "yes"}}, {"type": "way", "id": 652977986, "nodes": [6004512672, 8297556557, 6004512673, 6004512674, 6004512675, 6003392255, 6003392257, 6003392258, 6003392259, 6003392260, 6003392262, 6003392263, 6003392264, 6003392265, 6004512640, 6003392266, 6004512621, 6120228666, 6120228657, 6120228656, 6190860248, 6004512672], "tags": {"area": "yes", "bench": "yes", "public_transport": "platform", "railway": "platform", "ref": "6", "shelter": "yes"}}, {"type": "way", "id": 652977987, "nodes": [6004512624, 534436368, 6003392270, 1021462448, 534436369, 534436265, 6120228655, 6120228658, 6120228672, 6120228677, 6120228681, 6004512624], "tags": {"area": "yes", "public_transport": "platform", "railway": "platform", "ref": "5", "shelter": "yes"}}, {"type": "way", "id": 661272781, "nodes": [6190860246, 6004512659, 6004512658, 6004512657, 6004512656, 6004512644, 6004512655, 6004512619, 6120228670, 6120228682, 6144708865, 6120228678, 6190860250, 6190860246], "tags": {"area": "yes", "bench": "yes", "bin": "no", "lit": "yes", "public_transport": "platform", "railway": "platform", "ref": "8", "shelter": "yes", "tactile_paving": "yes"}}, {"type": "way", "id": 1150531687, "nodes": [10702635597, 551872944, 10702635598, 10702635599, 10702635600, 10702635597], "tags": {"amenity": "fast_food", "brand": "Upper Crust", "brand:wikidata": "Q7898585", "brand:wikipedia": "en:Upper Crust (restaurant chain)", "check_date": "2025-03-04", "check_date:opening_hours": "2024-11-17", "cuisine": "sandwich", "name": "Upper Crust", "opening_hours:signed": "no", "takeaway": "yes"}}, {"type": "way", "id": 1150531691, "nodes": [6121214733, 681266131, 10702669624, 10702669609, 10702669610, 6121214733], "tags": {"brand": "Marks & Spencer", "brand:short": "M&S", "brand:wikidata": "Q714491", "brand:wikipedia": "en:Marks & Spencer", "check_date": "2025-03-04", "check_date:opening_hours": "2024-07-21", "contact:website": "https://www.marksandspencer.com/stores/liverpool-lime-st-rail-simply-food-8141", "name": "M&S Simply Food", "opening_hours": "Mo-Fr 07:00-22:00; Sa,Su 08:00-22:00", "shop": "supermarket", "wheelchair": "yes"}}, {"type": "way", "id": 1150531695, "nodes": [10702669610, 10702669618, 10702669619, 6121214733, 10702669610], "tags": {"amenity": "fast_food", "brand": "Krispy Kreme", "brand:wikidata": "Q1192805", "check_date": "2025-03-04", "cuisine": "donut", "name": "Krispy Kreme", "note": "small vacant ground floor space under N part of 1st class lounge above", "takeaway": "yes"}}, {"type": "way", "id": 1169384325, "nodes": [10873837620, 10873837621, 2261421076, 10873837616, 10873837617, 2261421117, 2261421099, 2261421098, 2261421091, 10873837613, 2261421106, 2261421104, 2261421128, 10873837620], "tags": {"addr:city": "Liverpool", "addr:postcode": "L1 1RH", "addr:street": "Queen Square", "amenity": "restaurant", "brand": "ASK Italian", "brand:wikidata": "Q4807056", "building:part": "yes", "check_date": "2025-05-23", "cuisine": "italian", "name": "ASK Italian", "website": "https://www.askitalian.co.uk/italian/restaurants/liverpool"}}, {"type": "way", "id": 1174416069, "nodes": [10912583295, 10912583296, 10912583294, 2767005270, 10912583288, 10912583289, 10912583290, 10912583291, 10912583295], "tags": {"addr:city": "Liverpool", "addr:housenumber": "27", "addr:postcode": "L3 8HR", "addr:street": "London Road", "brand": "Go Local", "brand:wikidata": "Q120634011", "building:part": "retail", "fhrs:id": "683902", "level": "0", "name": "Go Local", "operator": "Go Local", "shop": "convenience"}}, {"type": "way", "id": 1174533115, "nodes": [10913976274, 10913976275, 4417907453, 4417907433, 4417907480, 4417907599, 4417907435, 10913976274], "tags": {"indoor": "room", "name": "International Food Store", "room": "retail", "shop": "convenience"}}, {"type": "way", "id": 1174533116, "nodes": [4417907438, 4417907622, 10913976276, 10913976277, 10913976278, 4417907462, 4417907601, 4417907438], "tags": {"addr:city": "Liverpool", "addr:housenumber": "48-50", "addr:postcode": "L3 5NF", "addr:street": "London Road", "clothes": "schoolwear", "indoor": "room", "name": "Trutex", "room": "retail", "shop": "clothes"}}, {"type": "way", "id": 1174533118, "nodes": [10913976283, 10913976284, 10913976285, 10913976286, 10913976280, 10913976279, 10913976283], "tags": {"amenity": "fast_food", "cuisine": "kebab", "indoor": "room", "name": "Shawarma", "room": "retail"}}, {"type": "way", "id": 1174533119, "nodes": [10913976284, 10913976287, 4417907649, 10913976283, 10913976284], "tags": {"amenity": "fast_food", "cuisine": "kebab", "indoor": "room", "name": "Abo Hassan Grill", "room": "retail"}}, {"type": "way", "id": 1174533122, "nodes": [2767005267, 10913976290, 10913976291, 10913976292, 2767005094, 2767005190, 2767005267], "tags": {"building:part": "retail", "name": "Marmaris Food store", "shop": "convenience"}}, {"type": "way", "id": 1174533123, "nodes": [10913976293, 10913976294, 10913976295, 10913976296, 10913976293], "tags": {"amenity": "fast_food", "building:part": "retail", "cuisine": "chicken;pizza", "name": "Freddy's"}}, {"type": "way", "id": 1178122540, "nodes": [4417907593, 10944259369, 2704294802, 10944259365, 10944259366, 4417907643, 4417907675, 4417907661, 4417907593], "tags": {"addr:city": "Liverpool", "addr:housename": "Arndale House", "addr:housenumber": "91-103", "addr:postcode": "L3 8JA", "addr:street": "London Road", "brand": "Tesco Express", "brand:wikidata": "Q98456772", "brand:wikipedia": "en:Tesco", "building:part": "retail", "contact:website": "https://www.tesco.com/store-locator/liverpool/91-93-london-rd", "fhrs:id": "509441", "name": "Tesco Express", "operator": "Tesco", "shop": "convenience", "source:addr": "FHRS Open Data"}}, {"type": "way", "id": 1273087350, "nodes": [2261421093, 2261421122, 9543046197, 9543046198, 12157837049, 9543046199, 12157837051, 12157837050, 12157815096, 9543046200, 4501084039, 4501083370, 4501084076, 4501084082, 11449842683, 4501084021, 6175652836, 6175652825, 9543046201, 9543046202, 12157805891, 2261421093], "tags": {"amenity": "bus_station", "bus": "yes", "name": "Queen Square Bus Station", "naptan:AtcoCode": "280G00000011", "public_transport": "station", "wheelchair": "yes"}}, {"type": "way", "id": 1313498454, "nodes": [533856662, 12157768492, 12157768493, 12157768494, 12157768495, 12157768496, 12157768497, 12157768498, 12157768499, 12157768500, 12157815001, 12157815002, 12157815003, 12157815004, 533856662], "tags": {"amenity": "shelter", "bench": "yes", "bin": "yes", "building": "yes", "bus": "yes", "highway": "bus_stop", "lit": "yes", "local_ref": "3", "naptan:AtcoCode": "2800S42023H", "naptan:CommonName": "QUEEN SQUARE BUS STATION", "naptan:Indicator": "STAND 3", "naptan:Landmark": "Queen Sq/Std 3", "naptan:NaptanCode": "merdgwpd", "naptan:Notes": "No Notes", "naptan:PlusbusZoneRef": "LVRPLCH", "naptan:ShortCommonName": "Queen Sq/Std 3", "naptan:Street": "QUEEN SQUARE STAND 3", "naptan:verified": "no", "public_transport": "platform", "ref": "3", "shelter": "yes", "shelter_type": "public_transport", "source": "naptan_import"}}, {"type": "way", "id": 1313498455, "nodes": [533856663, 12157815005, 12157815006, 12157815007, 12157815008, 12157815009, 12157815010, 12157815011, 12157815012, 12157815013, 12157815014, 12157815015, 12157815016, 12157815017, 533856663], "tags": {"amenity": "shelter", "bench": "yes", "bin": "yes", "building": "yes", "bus": "yes", "highway": "bus_stop", "lit": "yes", "local_ref": "2", "naptan:AtcoCode": "2800S42023I", "naptan:CommonName": "QUEEN SQUARE BUS STATION", "naptan:Indicator": "STAND 2", "naptan:Landmark": "QUEEN SQ STD 2", "naptan:NaptanCode": "merdgwpg", "naptan:Notes": "No Notes", "naptan:PlusbusZoneRef": "LVRPLCH", "naptan:ShortCommonName": "Queen Square", "naptan:Street": "QUEEN SQUARE STAND 2", "naptan:verified": "no", "public_transport": "platform", "ref": "2", "shelter": "yes", "shelter_type": "public_transport", "source": "naptan_import"}}, {"type": "way", "id": 1313498457, "nodes": [533856655, 12157815031, 12157825303, 12157815032, 12157815033, 12157815034, 12157815035, 12157815036, 12157815037, 12157815038, 12157815039, 12157815040, 12157815041, 12157815042, 12157815043, 533856655], "tags": {"amenity": "shelter", "bench": "yes", "bin": "yes", "building": "yes", "bus": "yes", "highway": "bus_stop", "lit": "yes", "local_ref": "4", "naptan:AtcoCode": "2800S42023A", "naptan:CommonName": "QUEEN SQUARE BUS STATION", "naptan:Indicator": "STAND 4", "naptan:Landmark": "QUEEN SQUARE STAND 4", "naptan:NaptanCode": "merdgwmg", "naptan:Notes": "No Notes", "naptan:PlusbusZoneRef": "LVRPLCH", "naptan:ShortCommonName": "Queen Square Std 4", "naptan:Street": "QUEEN SQUARE STAND 4", "naptan:verified": "no", "public_transport": "platform", "ref": "4", "shelter": "yes", "shelter_type": "public_transport", "source": "naptan_import"}}, {"type": "way", "id": 1313498458, "nodes": [533856661, 12157815044, 12157815045, 12157815046, 12157815047, 12157815048, 12157815049, 12157815050, 12157815051, 12157815052, 12157815053, 12157815054, 12157815055, 12157815056, 533856661], "tags": {"amenity": "shelter", "bench": "yes", "bin": "yes", "building": "yes", "bus": "yes", "highway": "bus_stop", "lit": "yes", "local_ref": "5", "naptan:AtcoCode": "2800S42023F", "naptan:CommonName": "QUEEN SQUARE BUS STATION", "naptan:Indicator": "STAND 5", "naptan:Landmark": "QUEEN SQUARE STAND 5", "naptan:NaptanCode": "merdgwpa", "naptan:Notes": "No Notes", "naptan:PlusbusZoneRef": "LVRPLCH", "naptan:ShortCommonName": "Queen Square Std 5", "naptan:Street": "QUEEN SQUARE STAND 5", "naptan:verified": "no", "public_transport": "platform", "ref": "5", "shelter": "yes", "shelter_type": "public_transport", "source": "naptan_import"}}, {"type": "way", "id": 1313498459, "nodes": [533856659, 12157815057, 12157815058, 12157815059, 12157815060, 12157825315, 12157815061, 12157815062, 12157815063, 12157815064, 12157815065, 12157815066, 12157815067, 12157815068, 12157815069, 533856659], "tags": {"amenity": "shelter", "bench": "yes", "bin": "yes", "building": "yes", "bus": "yes", "highway": "bus_stop", "lit": "yes", "local_ref": "6", "naptan:AtcoCode": "2800S42023E", "naptan:CommonName": "QUEEN SQUARE BUS STATION", "naptan:Indicator": "STAND 6", "naptan:Landmark": "QUEEN SQ STD 6", "naptan:NaptanCode": "merdgwmw", "naptan:Notes": "No Notes", "naptan:PlusbusZoneRef": "LVRPLCH", "naptan:ShortCommonName": "Queen Sq Std 6", "naptan:Street": "QUEEN SQUARE STAND 6", "naptan:verified": "no", "public_transport": "platform", "ref": "6", "shelter": "yes", "shelter_type": "public_transport", "source": "naptan_import"}}, {"type": "way", "id": 1313498460, "nodes": [533856657, 12157822824, 12157815070, 12157815071, 12157815072, 12157815073, 12157815074, 12157815075, 12157815076, 12157815077, 12157815078, 12157815079, 12157815080, 12157815081, 12157815082, 533856657], "tags": {"amenity": "shelter", "bench": "yes", "bin": "yes", "building": "yes", "bus": "yes", "highway": "bus_stop", "lit": "yes", "local_ref": "7", "naptan:AtcoCode": "2800S42023C", "naptan:CommonName": "QUEEN SQUARE BUS STATION", "naptan:Indicator": "STAND 7", "naptan:Landmark": "QUEEN SQUARE STAND 7", "naptan:NaptanCode": "merdgwmp", "naptan:Notes": "No Notes", "naptan:PlusbusZoneRef": "LVRPLCH", "naptan:ShortCommonName": "QueenSquare Std 7", "naptan:Street": "QUEEN SQUARE STAND 7", "naptan:verified": "no", "public_transport": "platform", "ref": "7", "shelter": "yes", "shelter_type": "public_transport", "source": "naptan_import"}}, {"type": "way", "id": 1313498461, "nodes": [533856658, 12157815083, 12157815084, 12157815085, 12157815086, 12157815087, 12157815088, 12157815089, 12157815090, 12157815091, 12157815092, 12157815093, 12157815094, 12157815095, 533856658], "tags": {"amenity": "shelter", "bench": "yes", "bin": "yes", "bus": "yes", "highway": "bus_stop", "lit": "yes", "local_ref": "8", "naptan:AtcoCode": "2800S42023D", "naptan:CommonName": "QUEEN SQUARE BUS STATION", "naptan:Indicator": "STAND 8", "naptan:Landmark": "QUEEN SQ STD 8", "naptan:NaptanCode": "merdgwmt", "naptan:Notes": "No Notes", "naptan:PlusbusZoneRef": "LVRPLCH", "naptan:ShortCommonName": "Queen Sq Std 8", "naptan:Street": "QUEEN SQUARE STAND 8", "naptan:verified": "no", "public_transport": "platform", "ref": "8", "shelter": "yes", "shelter_type": "public_transport", "source": "naptan_import"}}, {"type": "relation", "id": 9792747, "members": [{"type": "node", "ref": 25448278, "role": "stop"}, {"type": "way", "ref": 652977980, "role": "platform"}], "tags": {"public_transport": "stop_area", "type": "public_transport"}}, {"type": "relation", "id": 11211430, "members": [{"type": "way", "ref": 42739141, "role": "platform"}, {"type": "node", "ref": 6003536982, "role": "stop"}], "tags": {"name": "Liverpool Lime Street", "public_transport": "stop_area", "type": "public_transport"}}, {"type": "relation", "id": 14629378, "members": [{"type": "node", "ref": 6960405293, "role": ""}, {"type": "node", "ref": 25448278, "role": "stop"}, {"type": "node", "ref": 6003536982, "role": "stop"}, {"type": "node", "ref": 6003536983, "role": "stop"}, {"type": "node", "ref": 6003536981, "role": "stop"}, {"type": "node", "ref": 6003536980, "role": "stop"}, {"type": "node", "ref": 4261923762, "role": "stop"}, {"type": "node", "ref": 6004512647, "role": "stop"}, {"type": "node", "ref": 6004512646, "role": "stop"}, {"type": "node", "ref": 6004512645, "role": "stop"}, {"type": "node", "ref": 4319286756, "role": "stop"}, {"type": "node", "ref": 4319951101, "role": "stop"}, {"type": "way", "ref": 652977980, "role": "platform"}, {"type": "way", "ref": 42739141, "role": "platform"}, {"type": "way", "ref": 652977985, "role": "platform"}, {"type": "way", "ref": 42739145, "role": "platform"}, {"type": "way", "ref": 652977987, "role": "platform"}, {"type": "way", "ref": 652977986, "role": "platform"}, {"type": "way", "ref": 42739291, "role": "platform"}, {"type": "way", "ref": 661272781, "role": "platform"}, {"type": "way", "ref": 636797807, "role": "platform"}, {"type": "way", "ref": 636797800, "role": "platform"}, {"type": "way", "ref": 651521416, "role": "platform"}, {"type": "node", "ref": 6120201617, "role": ""}, {"type": "node", "ref": 4541108418, "role": ""}, {"type": "node", "ref": 6109282163, "role": ""}, {"type": "node", "ref": 6109282171, "role": ""}], "tags": {"name": "Lime Street", "public_transport": "stop_area", "type": "public_transport"}}]}